django_data_health_checks/__init__.py
django_data_health_checks/apps.py
django_data_health_checks/data_health_check.py
django_data_health_checks/mixins/__init__.py
django_data_health_checks/mixins/admin_context_mixin.py
django_data_health_checks/mixins/super_user_permission_mixin.py
django_data_health_checks/py.typed
django_data_health_checks/templates/admin/data_health_checks/data_health_checks.html
django_data_health_checks/urls.py
django_data_health_checks-0.0.4.dist-info/METADATA
django_data_health_checks-0.0.4.dist-info/WHEEL
django_data_health_checks-0.0.4.dist-info/RECORD
