Metadata-Version: 2.1
Name: django-data-health-checks
Version: 0.0.4
Summary: Write simple checks to identify and rectify potential integrity issues in your production data
Home-page: https://Flexonze.github.io/django-data-health-checks
License: MIT
Author: Flexonze
Author-email: flexonze@gmail.com
Requires-Python: >=3.8,<4.0
Classifier: Development Status :: 4 - Beta
Classifier: Intended Audience :: Developers
Classifier: License :: OSI Approved :: MIT License
Classifier: Operating System :: OS Independent
Classifier: Programming Language :: Python
Classifier: Programming Language :: Python :: 3
Classifier: Programming Language :: Python :: 3.8
Classifier: Programming Language :: Python :: 3.9
Classifier: Programming Language :: Python :: 3.10
Classifier: Programming Language :: Python :: 3.11
Classifier: Programming Language :: Python :: 3.12
Classifier: Topic :: Software Development :: Libraries :: Python Modules
Classifier: Typing :: Typed
Requires-Dist: django (>=4.2)
Project-URL: Documentation, https://Flexonze.github.io/django-data-health-checks
Project-URL: Repository, https://github.com/Flexonze/django-data-health-checks
